livekit/plugins/volcengine/__init__.py
livekit/plugins/volcengine/bigmodel_stt.py
livekit/plugins/volcengine/llm.py
livekit/plugins/volcengine/log.py
livekit/plugins/volcengine/py.typed
livekit/plugins/volcengine/realtime.py
livekit/plugins/volcengine/stt.py
livekit/plugins/volcengine/tts.py
livekit/plugins/volcengine/utils.py
livekit/plugins/volcengine/version.py
livekit_plugins_volcengine-1.3.0.dist-info/METADATA
livekit_plugins_volcengine-1.3.0.dist-info/WHEEL
livekit_plugins_volcengine-1.3.0.dist-info/RECORD
