Metadata-Version: 2.4
Name: livekit-plugins-volcengine
Version: 1.3.0
Summary: LiveKit Agent Plugins for Volcengine
Author-email: wangmengdi <790990241@qq.com>
Keywords: audio,livekit,realtime,video,webrtc
Classifier: Intended Audience :: Developers
Classifier: License :: OSI Approved :: Apache Software License
Classifier: Programming Language :: Python :: 3
Classifier: Programming Language :: Python :: 3 :: Only
Classifier: Programming Language :: Python :: 3.9
Classifier: Programming Language :: Python :: 3.10
Classifier: Topic :: Multimedia :: Sound/Audio
Classifier: Topic :: Multimedia :: Video
Classifier: Topic :: Scientific/Engineering :: Artificial Intelligence
Requires-Python: >=3.9
Requires-Dist: livekit-agents==1.2.9
Requires-Dist: numpy
Requires-Dist: openai>=1.75.0
Requires-Dist: osc-data==0.2.2
Requires-Dist: pydantic
